tests/test.py
zeitpy/__init__.py
zeitpy/core.py
zeitpy-0.1.2.dist-info/licenses/LICENSE
zeitpy-0.1.2.dist-info/METADATA
zeitpy-0.1.2.dist-info/WHEEL
zeitpy-0.1.2.dist-info/top_level.txt
zeitpy-0.1.2.dist-info/RECORD
