Metadata-Version: 2.4
Name: zeitpy
Version: 0.1.2
Summary: A package for time series analysis — from EDA to forecasting and performance assessment.
Author-email: Domingos de Eulária <you@example.com>
License: MIT License
Project-URL: Homepage, https://github.com/domingosdeeulariadumba.com/ZeitPy
Requires-Python: >=3.12.7
License-File: LICENSE
Requires-Dist: numpy>=1.26.4
Requires-Dist: pandas>=2.2.2
Requires-Dist: scipy>=1.13.1
Requires-Dist: scikit-learn>=1.5.1
Requires-Dist: matplotlib>=3.9.2
Requires-Dist: seaborn>=0.13.2
Requires-Dist: statsmodels>=0.14.2
Dynamic: license-file
